naturalpy/__init__.py
naturalpy/core.py
naturalpy-0.1.1.dist-info/licenses/LICENSE
naturalpy-0.1.1.dist-info/METADATA
naturalpy-0.1.1.dist-info/WHEEL
naturalpy-0.1.1.dist-info/top_level.txt
naturalpy-0.1.1.dist-info/RECORD
