Metadata-Version: 2.4
Name: naturalpy
Version: 0.1.1
Summary: A minimalistic natural programming inspired library for easy integration of LLMs into Python in a more pythonic way.
Author-email: Isuru Wijesiri <imwijesiri@gmial.com>
License: MIT
Project-URL: Homepage, https://github.com/IsuruMaduranga/natural-python
Project-URL: Bug Tracker, https://github.com/IsuruMaduranga/natural-python/issues
Classifier: Programming Language :: Python :: 3
Classifier: License :: OSI Approved :: MIT License
Classifier: Operating System :: OS Independent
Requires-Python: >=3.11
License-File: LICENSE
Requires-Dist: openai>=1.70.0
Requires-Dist: pydantic>=2.11.0
Requires-Dist: instructor>=1.7.8
Dynamic: license-file
